{"@odata.context":"/redfish/v1/$metadata#Sessions","@odata.id":"/redfish/v1/SessionService/Sessions/","@odata.type":"#SessionCollection.SessionCollection","Description":"Manager User Sessions","Items":[{"@odata.context":"/redfish/v1/$metadata#SessionService/Sessions/Members/$entity","@odata.id":"/redfish/v1/SessionService/Sessions/dcmscan5e94e609610624dd/","@odata.type":"#Session.1.0.0.Session","Description":"Manager User Session","Id":"dcmscan5e94e609610624dd","Name":"User Session","Oem":{"Hp":{"@odata.type":"#HpiLOSession.1.0.0.HpiLOSession","AccessTime":"2020-04-15T18:51:38Z","LoginTime":"2020-04-13T22:22:01Z","MySession":false,"Type":"HpiLOSession.1.0.0","UserExpires":"2020-04-15T18:56:38Z","UserIP":"10.239.43.96","UserTag":"IPMI/RMCP","UserType":"Local"}},"Type":"Session.1.0.0","UserName":"dcmscan","links":{"self":{"href":"/redfish/v1/SessionService/Sessions/dcmscan5e94e609610624dd/"}}},{"@odata.context":"/redfish/v1/$metadata#SessionService/Sessions/Members/$entity","@odata.id":"/redfish/v1/SessionService/Sessions/dcm5e77821f07ae147b/","@odata.type":"#Session.1.0.0.Session","Description":"Manager User Session","Id":"dcm5e77821f07ae147b","Name":"User Session","Oem":{"Hp":{"@odata.type":"#HpiLOSession.1.0.0.HpiLOSession","AccessTime":"2020-04-15T18:51:31Z","LoginTime":"2020-03-22T15:19:59Z","MySession":false,"Type":"HpiLOSession.1.0.0","UserExpires":"2020-04-15T18:56:31Z","UserIP":"10.239.151.4","UserTag":"IPMI/RMCP","UserType":"Local"}},"Type":"Session.1.0.0","UserName":"dcm","links":{"self":{"href":"/redfish/v1/SessionService/Sessions/dcm5e77821f07ae147b/"}}},{"@odata.context":"/redfish/v1/$metadata#SessionService/Sessions/Members/$entity","@odata.id":"/redfish/v1/SessionService/Sessions/dcm5e974a35726e978d/","@odata.type":"#Session.1.0.0.Session","Description":"Manager User Session","Id":"dcm5e974a35726e978d","Name":"User Session","Oem":{"Hp":{"@odata.type":"#HpiLOSession.1.0.0.HpiLOSession","AccessTime":"2020-04-15T18:50:47Z","LoginTime":"2020-04-15T17:53:57Z","MySession":false,"Type":"HpiLOSession.1.0.0","UserExpires":"2020-04-15T18:55:47Z","UserIP":"10.239.98.171","UserTag":"IPMI/RMCP","UserType":"Local"}},"Type":"Session.1.0.0","UserName":"dcm","links":{"self":{"href":"/redfish/v1/SessionService/Sessions/dcm5e974a35726e978d/"}}},{"@odata.context":"/redfish/v1/$metadata#SessionService/Sessions/Members/$entity","@odata.id":"/redfish/v1/SessionService/Sessions/dcm5e9608a3d5c28f5c/","@odata.type":"#Session.1.0.0.Session","Description":"Manager User Session","Id":"dcm5e9608a3d5c28f5c","Name":"User Session","Oem":{"Hp":{"@odata.type":"#HpiLOSession.1.0.0.HpiLOSession","AccessTime":"2020-04-15T18:51:51Z","LoginTime":"2020-04-14T19:01:55Z","MySession":false,"Type":"HpiLOSession.1.0.0","UserExpires":"2020-04-15T18:56:51Z","UserIP":"10.239.151.3","UserTag":"IPMI/RMCP","UserType":"Local"}},"Type":"Session.1.0.0","UserName":"dcm","links":{"self":{"href":"/redfish/v1/SessionService/Sessions/dcm5e9608a3d5c28f5c/"}}},{"@odata.context":"/redfish/v1/$metadata#SessionService/Sessions/Members/$entity","@odata.id":"/redfish/v1/SessionService/Sessions/dcm5e9655348e978d50/","@odata.type":"#Session.1.0.0.Session","Description":"Manager User Session","Id":"dcm5e9655348e978d50","Name":"User Session","Oem":{"Hp":{"@odata.type":"#HpiLOSession.1.0.0.HpiLOSession","AccessTime":"2020-04-15T18:51:30Z","LoginTime":"2020-04-15T00:28:36Z","MySession":false,"Type":"HpiLOSession.1.0.0","UserExpires":"2020-04-15T18:56:30Z","UserIP":"10.239.172.58","UserTag":"IPMI/RMCP","UserType":"Local"}},"Type":"Session.1.0.0","UserName":"dcm","links":{"self":{"href":"/redfish/v1/SessionService/Sessions/dcm5e9655348e978d50/"}}},{"@odata.context":"/redfish/v1/$metadata#SessionService/Sessions/Members/$entity","@odata.id":"/redfish/v1/SessionService/Sessions/dcm5e975124ea7ef9db/","@odata.type":"#Session.1.0.0.Session","Description":"Manager User Session","Id":"dcm5e975124ea7ef9db","Name":"User Session","Oem":{"Hp":{"@odata.type":"#HpiLOSession.1.0.0.HpiLOSession","AccessTime":"2020-04-15T18:23:33Z","LoginTime":"2020-04-15T18:23:32Z","MySession":false,"Type":"HpiLOSession.1.0.0","UserExpires":"2020-04-15T18:28:33Z","UserIP":"10.238.1.109","UserTag":"Web UI","UserType":"Local"}},"Type":"Session.1.0.0","UserName":"dcm","links":{"self":{"href":"/redfish/v1/SessionService/Sessions/dcm5e975124ea7ef9db/"}}},{"@odata.context":"/redfish/v1/$metadata#SessionService/Sessions/Members/$entity","@odata.id":"/redfish/v1/SessionService/Sessions/dcm5e9757cc06666666/","@odata.type":"#Session.1.0.0.Session","Description":"Manager User Session","Id":"dcm5e9757cc06666666","Name":"User Session","Oem":{"Hp":{"@odata.type":"#HpiLOSession.1.0.0.HpiLOSession","AccessTime":"2020-04-15T18:51:56Z","LoginTime":"2020-04-15T18:51:56Z","MySession":true,"Privileges":{"LoginPriv":true,"RemoteConsolePriv":true,"UserConfigPriv":true,"VirtualMediaPriv":true,"VirtualPowerAndResetPriv":true,"iLOConfigPriv":true},"Type":"HpiLOSession.1.0.0","UserExpires":"2020-04-15T18:56:56Z","UserIP":"10.239.4.80","UserTag":"REST","UserType":"Local"}},"Type":"Session.1.0.0","UserName":"dcm","links":{"self":{"href":"/redfish/v1/SessionService/Sessions/dcm5e9757cc06666666/"}}}],"MemberType":"Session.1","Members":[{"@odata.id":"/redfish/v1/SessionService/Sessions/dcmscan5e94e609610624dd/"},{"@odata.id":"/redfish/v1/SessionService/Sessions/dcm5e77821f07ae147b/"},{"@odata.id":"/redfish/v1/SessionService/Sessions/dcm5e974a35726e978d/"},{"@odata.id":"/redfish/v1/SessionService/Sessions/dcm5e9608a3d5c28f5c/"},{"@odata.id":"/redfish/v1/SessionService/Sessions/dcm5e9655348e978d50/"},{"@odata.id":"/redfish/v1/SessionService/Sessions/dcm5e975124ea7ef9db/"},{"@odata.id":"/redfish/v1/SessionService/Sessions/dcm5e9757cc06666666/"}],"Members@odata.count":7,"Name":"Sessions","Oem":{"Hp":{"@odata.type":"#HpiLOSessionsSummary.1.0.0.HpiLOSessionsSummary","Type":"HpiLOSessionsSummary.1.0.0","links":{"MySession":{"href":"/redfish/v1/SessionService/Sessions/dcm5e9757cc06666666/"}}}},"Total":7,"Type":"Collection.1.0.0","links":{"Member":[{"href":"/redfish/v1/SessionService/Sessions/dcmscan5e94e609610624dd/"},{"href":"/redfish/v1/SessionService/Sessions/dcm5e77821f07ae147b/"},{"href":"/redfish/v1/SessionService/Sessions/dcm5e974a35726e978d/"},{"href":"/redfish/v1/SessionService/Sessions/dcm5e9608a3d5c28f5c/"},{"href":"/redfish/v1/SessionService/Sessions/dcm5e9655348e978d50/"},{"href":"/redfish/v1/SessionService/Sessions/dcm5e975124ea7ef9db/"},{"href":"/redfish/v1/SessionService/Sessions/dcm5e9757cc06666666/"}],"self":{"href":"/redfish/v1/SessionService/Sessions/"}}}