{"@odata.context":"/redfish/v1/$metadata#HpeHttpsCert.HpeHttpsCert","@odata.etag":"W/\"7A1717BD\"","@odata.id":"/redfish/v1/Managers/1/SecurityService/HttpsCert/","@odata.type":"#HpeHttpsCert.v2_0_0.HpeHttpsCert","Id":"HttpsCert","Actions":{"#HpeHttpsCert.GenerateCSR":{"target":"/redfish/v1/Managers/1/SecurityService/HttpsCert/Actions/HpeHttpsCert.GenerateCSR/"},"#HpeHttpsCert.ImportCertificate":{"target":"/redfish/v1/Managers/1/SecurityService/HttpsCert/Actions/HpeHttpsCert.ImportCertificate/"}},"CertificateSigningRequest":null,"X509CertificateInformation":{"Issuer":"CN = Default Issuer (Do not trust), O = Hewlett Packard Enterprise, OU = ISS, L = Houston, ST = Texas, C = US","SerialNumber":"79:c5:a2:00:cf:b3:c7:7c","Subject":"CN = ILO6CU747C51S, O = Hewlett Packard Enterprise, OU = ISS, L = Houston, ST = Texas, C = US","ValidNotAfter":"2033-11-21T21:23:12Z","ValidNotBefore":"2018-11-22T21:23:12Z"}}