{"@odata.context":"/redfish/v1/$metadata#LogEntry.LogEntry","@odata.etag":"W/\"AD20CA3A\"","@odata.id":"/redfish/v1/Managers/1/LogServices/IEL/Entries/265/","@odata.type":"#LogEntry.v1_1_0.LogEntry","Id":"265","Created":"2020-05-11T00:02:00Z","EntryType":"Oem","Message":"Browser login: xfqian - 10.239.151.3(DNS name not found).","Name":"iLO Event Log","Oem":{"Hpe":{"@odata.context":"/redfish/v1/$metadata#HpeLogEntry.HpeLogEntry","@odata.type":"#HpeLogEntry.v2_2_0.HpeLogEntry","Categories":["Security","Administration"],"Class":35,"ClassDescription":"iLO 5","Code":1017,"Count":171,"EventNumber":1019947,"Severity":"Informational","Updated":"2020-05-11T00:02:59Z"}},"OemRecordFormat":"Hpe-iLOEventLog","Severity":"OK"}