{"associatedResource":{"associationType":"MANAGED_BY","resourceCategory":"alerts","resourceName":"Security","resourceUri":"/rest/certificates/servers/36395747-504E-3430-3335-202020202020"},"associatedTaskUri":null,"completedSteps":0,"computedPercentComplete":100,"created":"2021-04-25T08:03:26.606Z","data":{},"eTag":"\"1\"","expectedDuration":0,"hidden":false,"modified":"2021-04-25T08:03:27.103Z","name":"Adding Resources","owner":"certs","parentTaskUri":null,"percentComplete":100,"progressUpdates":[],"startTime":"2021-04-25T08:03:26.606Z","stateReason":null,"taskErrors":[],"taskOutput":[],"taskState":"Completed","taskStatus":"MonitoredResources successfully added/updated.","taskType":"Background","totalSteps":0,"uri":"/rest/tasks/c81f0b90-bfd4-44a3-af1c-5ef9bddca732","userInitiated":false,"category":"tasks","type":"TaskResourceV3","isCancellable":false}