{"type":"EventResourceV3","uri":"/rest/events/533546","category":"events","eTag":"2020-06-21T11:48:59.263Z","created":"2020-06-21T11:48:59.263Z","modified":"2020-06-21T11:48:59.263Z","healthCategory":"ha-nodes","description":"Changes made on CZJ9260730, appliance bay 1 are being synchronized to CZJ9260730, appliance bay 2.","eventTypeID":"HACluster.StorageSynchronization","eventDetails":[{"eventItemName":"correctiveAction","eventItemValue":"No action is necessary. The appliance cluster will be highly available when synchronization completes.","varBindOrderIndex":-1,"isThisVarbindData":false,"eventItemDescription":null,"eventItemSnmpOid":null},{"eventItemName":"resourceUri","eventItemValue":"/rest/appliance/ha-nodes/CN791303ZS","varBindOrderIndex":-1,"isThisVarbindData":false,"eventItemDescription":null,"eventItemSnmpOid":null},{"eventItemName":"locked","eventItemValue":"true","varBindOrderIndex":-1,"isThisVarbindData":false,"eventItemDescription":null,"eventItemSnmpOid":null}],"rxTime":"2020-06-21T11:48:59.254Z","processed":true,"severity":"Warning","urgency":"High","serviceEventSource":false,"serviceEventDetails":null}