{"associatedResource":{"associationType":"MANAGED_BY","resourceCategory":"server-hardware","resourceName":"CZJ9260730, bay 3","resourceUri":"/rest/server-hardware/39313738-3034-5A43-4A39-323630373232"},"associatedTaskUri":null,"completedSteps":2,"computedPercentComplete":100,"created":"2020-06-21T10:56:39.380Z","data":{},"eTag":"\"3\"","expectedDuration":5,"hidden":false,"modified":"2020-06-21T10:56:46.019Z","name":"Refresh port map interconnect links","owner":"System","parentTaskUri":null,"percentComplete":100,"progressUpdates":[{"id":0,"statusUpdate":"Refresh adapter and port information.","timestamp":"2020-06-21T10:56:40.072Z"}],"startTime":"2020-06-21T10:56:40.074Z","stateReason":null,"taskErrors":[],"taskOutput":[],"taskState":"Completed","taskStatus":"Refresh port map interconnect links complete.","taskType":"User","totalSteps":2,"uri":"/rest/tasks/cb76d800-0f70-44df-9506-f116d68570cb","userInitiated":true,"category":"tasks","type":"TaskResourceV3","isCancellable":false}