{"type":"interconnect-typeV5","uri":"/rest/interconnect-types/537975d6-c123-4250-bfda-4ca10070cb97","category":"interconnect-types","eTag":"09618b42-3b8a-4636-a52b-3fabbb9633ef","created":"2019-10-14T07:11:35.225Z","modified":"2019-10-14T07:11:35.226Z","minimumFirmwareVersion":"0.0","maximumFirmwareVersion":"0.0","partNumber":"Unsupported","interconnectCapabilities":{"maxBandwidthInGbps":null,"capabilities":[]},"downlinkPortCapability":{"type":"downlink-port-capability","uri":null,"category":null,"eTag":null,"created":null,"modified":null,"totalSubPort":null,"maxBandwidthInGbps":null,"portCapabilities":[],"downlinkSubPorts":{},"description":null,"state":null,"status":null,"name":null},"downlinkCount":0,"portInfos":[],"otherFamilyMembers":null,"taaCompliant":false,"switchTemplatePartNumber":null,"shortModelName":null,"unsupportedCapabilities":[],"description":null,"state":"Active","status":"OK","name":"Unsupported"}