{"associatedResource":{"associationType":"MANAGED_BY","resourceCategory":"interconnects","resourceName":"CZJ9260730, interconnect 6","resourceUri":"/rest/interconnects/d92aa3eb-9170-4621-9593-e012eafdd5f8"},"associatedTaskUri":null,"completedSteps":4,"computedPercentComplete":100,"created":"2020-06-22T13:27:43.603Z","data":{},"eTag":"\"35\"","expectedDuration":0,"hidden":false,"modified":"2020-06-22T13:46:32.672Z","name":"Update firmware","owner":"administrator","parentTaskUri":"/rest/tasks/d97becb9-418e-4445-9b74-c2040d6f4f85","percentComplete":100,"progressUpdates":[{"id":0,"statusUpdate":"Firmware update initiated from 1.5.0.1004 to 1.6.0.1004","timestamp":"2020-06-22T13:27:43.759Z"},{"id":1,"statusUpdate":"Stage firmware started","timestamp":"2020-06-22T13:27:45.080Z"},{"id":2,"statusUpdate":"Stage firmware 30% completed","timestamp":"2020-06-22T13:27:47.271Z"},{"id":3,"statusUpdate":"Stage firmware 50% completed","timestamp":"2020-06-22T13:27:48.369Z"},{"id":4,"statusUpdate":"Stage firmware 80% completed","timestamp":"2020-06-22T13:27:50.027Z"},{"id":5,"statusUpdate":"Stage firmware completed","timestamp":"2020-06-22T13:27:51.818Z"},{"id":6,"statusUpdate":"Activation will start once staging completes for all the interconnects","timestamp":"2020-06-22T13:27:51.913Z"},{"id":7,"statusUpdate":"Activate firmware started","timestamp":"2020-06-22T13:28:48.302Z"},{"id":8,"statusUpdate":"Initiating loading of images on the interconnect / reboot","timestamp":"2020-06-22T13:28:55.928Z"},{"id":9,"statusUpdate":"Interconnect back online / verification in progress","timestamp":"2020-06-22T13:36:15.003Z"},{"id":10,"statusUpdate":"Activate firmware completed","timestamp":"2020-06-22T13:36:16.002Z"}],"startTime":"2020-06-22T13:27:43.604Z","stateReason":"skipConfigRequired","taskErrors":[],"taskOutput":[],"taskState":"Completed","taskStatus":"Successfully activated firmware on the interconnect CZJ9260730, interconnect 6","taskType":"User","totalSteps":4,"uri":"/rest/tasks/e1566ca2-e124-4199-afd8-d926e38f5a96","userInitiated":true,"category":"tasks","type":"TaskResourceV3","isCancellable":false}