{"type":"EventResourceV3","uri":"/rest/events/4002331","category":"events","eTag":"2021-04-26T07:06:37.479Z","created":"2021-04-26T07:06:37.479Z","modified":"2021-04-26T07:06:37.479Z","healthCategory":"sas-logical-interconnects","description":"The firmware on the interconnects and/or drive enclosures managed by {\"name\":\"LEG-QGPTSYN01-LIG-QGPTSYN01-SAS-1\",\"uri\":\"/rest/sas-logical-interconnects/c030ac2b-405f-4225-923d-5f77fe084bef\"} does not match the firmware versions specified in the firmware baseline.","eventTypeID":"firmwareupdate.baseline","eventDetails":[{"eventItemName":"correctiveAction","eventItemValue":"Update firmware for logical interconnect {\"name\":\"LEG-QGPTSYN01-LIG-QGPTSYN01-SAS-1\",\"uri\":\"/rest/sas-logical-interconnects/c030ac2b-405f-4225-923d-5f77fe084bef\"}.","varBindOrderIndex":-1,"isThisVarbindData":false,"eventItemDescription":null,"eventItemSnmpOid":null},{"eventItemName":"resourceUri","eventItemValue":"/rest/sas-logical-interconnects/c030ac2b-405f-4225-923d-5f77fe084bef","varBindOrderIndex":-1,"isThisVarbindData":false,"eventItemDescription":null,"eventItemSnmpOid":null},{"eventItemName":"clearPriorEvents","eventItemValue":"true","varBindOrderIndex":-1,"isThisVarbindData":false,"eventItemDescription":null,"eventItemSnmpOid":null}],"rxTime":"2021-04-26T07:06:37.472Z","processed":true,"severity":"Warning","urgency":"Medium","serviceEventSource":false,"serviceEventDetails":null}