{"associatedResource":{"associationType":"MANAGED_BY","resourceCategory":"interconnects","resourceName":"CZJ9260730, interconnect 6","resourceUri":"/rest/interconnects/d92aa3eb-9170-4621-9593-e012eafdd5f8"},"associatedTaskUri":null,"completedSteps":0,"computedPercentComplete":100,"created":"2020-06-29T09:58:48.782Z","data":{"task-category":"ConnectionDeployment","ConnectionInstanceUri":"/rest/connections/85f7bfd6-1e22-4cf6-8800-6f8a4182c14b"},"eTag":"\"1\"","expectedDuration":0,"hidden":false,"modified":"2020-06-29T09:59:00.528Z","name":"Update","owner":"dctcraymon@qatargas.com.qa","parentTaskUri":"/rest/tasks/6a21dc1c-5ffd-4931-8553-5b903fc9ea6e","percentComplete":100,"progressUpdates":[{"id":0,"statusUpdate":"Configuring connection on downlink port 3, subport 3","timestamp":"2020-06-29T09:58:48.782Z"}],"startTime":"2020-06-29T09:58:48.783Z","stateReason":null,"taskErrors":[],"taskOutput":[],"taskState":"Completed","taskStatus":"Completed task /rest/tasks/fa0035f6-1cb5-4632-83b1-ae3730d69cdf associated with connection 85f7bfd6-1e22-4cf6-8800-6f8a4182c14b","taskType":"User","totalSteps":0,"uri":"/rest/tasks/fa0035f6-1cb5-4632-83b1-ae3730d69cdf","userInitiated":true,"category":"tasks","type":"TaskResourceV3","isCancellable":false}