{"associatedResource":{"associationType":"MANAGED_BY","resourceCategory":"sas-logical-jbods","resourceName":"Bay5 (9770)","resourceUri":"/rest/sas-logical-jbods/8061a7fa-9ad1-48a7-91dd-cb84cb327ec2"},"associatedTaskUri":null,"completedSteps":0,"computedPercentComplete":100,"created":"2020-06-29T09:54:16.679Z","data":{},"eTag":"\"5\"","expectedDuration":0,"hidden":false,"modified":"2020-06-29T09:54:34.225Z","name":"Create","owner":"dctcraymon@qatargas.com.qa","parentTaskUri":"/rest/tasks/e76eebed-1159-4581-ac39-c71c13f3e897","percentComplete":100,"progressUpdates":[{"id":0,"statusUpdate":"Allocate drives from the drive enclosure.","timestamp":"2020-06-29T09:54:16.978Z"},{"id":1,"statusUpdate":"Clearing meta data on drive(s).","timestamp":"2020-06-29T09:54:16.994Z"},{"id":2,"statusUpdate":"Configuring logical JBOD.","timestamp":"2020-06-29T09:54:17.481Z"},{"id":3,"statusUpdate":"Created SAS logical JBOD.","timestamp":"2020-06-29T09:54:34.225Z"}],"startTime":"2020-06-29T09:54:16.776Z","stateReason":null,"taskErrors":[],"taskOutput":[],"taskState":"Completed","taskStatus":null,"taskType":"User","totalSteps":0,"uri":"/rest/tasks/dd8cfd18-2f91-43d0-bdf1-ba9b73de4442","userInitiated":true,"category":"tasks","type":"TaskResourceV3","isCancellable":false}