{"error":{"@Message.ExtendedInfo":[{"Message":"A required license is missing or expired.","MessageArgs":[],"MessageArgs@odata.count":0,"MessageId":"IDRAC.2.1.LIC501","RelatedProperties":[],"RelatedProperties@odata.count":0,"Resolution":"Obtain an appropriate license from Dell Digital Locker and then try again. If the problem persists, refer to the product documentation or contact technical support.","Severity":"Warning"}],"code":"Base.1.5.GeneralError","message":"A general error has occurred. See ExtendedInfo for more information"}}