{ "@odata.context": "/redfish/v1/$metadata#EthernetInterfaceCollection.EthernetInterfaceCollection", "@odata.id": "/redfish/v1/Managers/Self/EthernetInterfaces/0894EF5E92FC", "@odata.type": "#EthernetInterface.v1_5_0.EthernetInterface", "Name": "Manager Ethernet Interface", "Id": "0894EF5E92FC", "PermanentMACAddress": "08:94:EF:5E:92:FC", "MACAddress": "08:94:EF:5E:92:FC", "Oem": { "BMC": { "IPV4Enabled": true, "IPV6Enabled": true, "InterfaceName": "eth0", "ChannelIndex": 1 } }, "InterfaceEnabled": true, "SpeedMbps": 100, "AutoNeg": true, "FullDuplex": true, "MTUSize": 1500, "LinkStatus": "LinkUp", "MaxIPv6StaticAddresses": 16, "VLAN": { "VLANEnable": false, "VLANId": 0 }, "IPv4Addresses": [ { "Address": "10.8.32.198", "SubnetMask": "255.255.255.0", "Gateway": "10.8.32.254", "AddressOrigin": "DHCP" } ], "DHCPv4": { "FallbackAddress": "None", "DHCPEnabled": true }, "DHCPv6": { "OperatingMode": "DHCPv6" }, "StatelessAddressAutoConfig": { "IPv4AutoConfigEnabled": false, "IPv6AutoConfigEnabled": true }, "IPv6StaticAddresses": [ ], "IPv6Addresses": [ { "AddressOrigin": "DHCPv6", "Address": "2001::edbb:d3f6:159d:8a34", "PrefixLength": 64 }, { "Address": "fe80::a94:efff:fe5e:92fc", "PrefixLength": 64, "AddressOrigin": "LinkLocal" } ], "IPv6DefaultGateway": "::", "IPv6StaticDefaultGateways": [ ], "NameServers": [ "10.8.200.235", "10.8.200.236", "::" ], "HostName": "NETTRIX0894EF5E92FC", "FQDN": "NETTRIX0894EF5E92FC.", "Status": { "State": "Enabled", "Health": "OK", "HealthRollup": "OK" } }