{"MessageArgs":["RAID subsystem","3"],"Id":"4702","Message":"Inventory data collecting and processing complete for RAID subsystem, sequence number is 3.","EntryType":"Oem","Name":"LogEntry","@odata.context":"\/redfish\/v1\/$metadata#LogEntry.LogEntry","Description":"This resource is used to represent a log entry for log services for a Redfish implementation.","Oem":{"Lenovo":{"ReportingChain":"","IsLocalEvent":true,"RawDebugLogURL":"","AffectedIndicatorLEDs":[],"EventFlag":0,"AuxiliaryData":"","Source":"System","FailingFRU":[{"FRUSerialNumber":"","FRUNumber":""}],"TSLVersion":"0","CommonEventID":"FQXSPDM4010I","Hidden":true,"EventID":"0x400000c000000000","EventSequenceNumber":4682,"EventType":0,"@odata.type":"#LenovoLogEntry.v1_0_0.StandardLogEntry","LenovoMessageID":"Lenovo0192","RelatedEventID":"","Serviceable":"Not Serviceable"}},"@odata.type":"#LogEntry.v1_4_0.LogEntry","OemRecordFormat":"Lenovo","Severity":"OK","@odata.etag":"\"5951ef8cfcaad44a6960c8d1a12bd2b0\"","@odata.id":"\/redfish\/v1\/Systems\/1\/LogServices\/StandardLog\/Entries\/4702","Created":"2020-05-07T09:54:53.349+00:00"}