{"@odata.id":"\/redfish\/v1\/Managers\/1\/Oem\/Lenovo\/Configuration","BackupStatus":"No backup action","Name":"Configuration","@odata.context":"\/redfish\/v1\/$metadata#LenovoConfigurationService.LenovoConfigurationService","@odata.type":"#LenovoConfigurationService.v1_0_0.LenovoConfigurationService","RestoreStatus":"No restore action","Id":"Configuration","@odata.etag":"\"16fe5f48fbdcc11a77154da87d324843\"","Actions":{"#LenovoConfigurationService.RestoreConfiguration":{"target":"\/redfish\/v1\/Managers\/1\/Oem\/Lenovo\/Configuration\/Actions\/LenovoConfigurationService.RestoreConfiguration","title":"RestoreConfiguration"},"#LenovoConfigurationService.BackupConfiguration":{"target":"\/redfish\/v1\/Managers\/1\/Oem\/Lenovo\/Configuration\/Actions\/LenovoConfigurationService.BackupConfiguration","title":"BackupConfiguration"},"#LenovoConfigurationService.ResetToDefault":{"target":"\/redfish\/v1\/Managers\/1\/Oem\/Lenovo\/Configuration\/Actions\/LenovoConfigurationService.ResetToDefault","title":"ResetToDefault"}},"Description":"This resource is used to represent a configuration service for the manager for a Redfish implementation."}