{"@odata.id":"\/redfish\/v1\/Chassis\/1\/Oem\/Lenovo\/Sensors\/111L0","EntityInstance":15,"Assertion":"Deassert","Id":"111L0","Description":"This resource is used to represent a sensor for a Redfish implementation.","RecordType":2,"OwnerID":32,"OwnerLUN":0,"Name":"Drive 15","State":32768,"SensorType":"Drive Slot\/Bay","ReadingType":111,"Reading":0,"@odata.etag":"\"03d407d4e393f3e46abedc4ca7a064e8\"","@odata.type":"#LenovoSensor.v1_0_0.LenovoSensor","EntityID":4,"SensorTypeNumber":13,"BaseUnit":"0","SensorNumber":111,"@odata.context":"\/redfish\/v1\/$metadata#LenovoSensor.LenovoSensor"}