{"@odata.context":"/redfish/v1/$metadata#Systems/Members/1/PCIDevices/Members/$entity","@odata.id":"/redfish/v1/Systems/1/PCIDevices/2/","@odata.type":"#HpServerPciDevice.1.0.0.HpServerPciDevice","BusNumber":2,"ClassCode":2,"DeviceID":5719,"DeviceInstance":1,"DeviceLocation":"Embedded","DeviceNumber":0,"DeviceSubInstance":2,"DeviceType":"Embedded LOM","FunctionNumber":1,"Id":"2","Name":"HP Ethernet 1Gb 4-port 331i Adapter - NIC","SegmentNumber":0,"StructuredName":"NIC.LOM.1.2","SubclassCode":0,"SubsystemDeviceID":8894,"SubsystemVendorID":4156,"Type":"HpServerPciDevice.1.0.0","UEFIDevicePath":"PciRoot(0x0)/Pci(0x1C,0x4)/Pci(0x0,0x1)","VendorID":5348,"links":{"self":{"href":"/redfish/v1/Systems/1/PCIDevices/2/"}}}