{"BootSources":[{"BootString":"sles-secureboot","CorrelatableID":"PciRoot(0x0)/Pci(0x1,0x0)/Pci(0x0,0x0)","StructuredBootString":"HD.Emb.1.6","UEFIDevicePath":"PciRoot(0x0)/Pci(0x1,0x0)/Pci(0x0,0x0)/Scsi(0x0,0x0)/HD(3,GPT,91002AE5-E38D-4AE7-95F5-65C107287A02,0xEC1800,0x52000)/\\EFI\\sles\\shim.efi"},{"BootString":"grub-secureboot","CorrelatableID":"PciRoot(0x0)/Pci(0x1,0x0)/Pci(0x0,0x0)","StructuredBootString":"HD.Emb.1.5","UEFIDevicePath":"PciRoot(0x0)/Pci(0x1,0x0)/Pci(0x0,0x0)/Scsi(0x0,0x0)/HD(3,GPT,91002AE5-E38D-4AE7-95F5-65C107287A02,0xEC1800,0x52000)/\\EFI\\grub\\shim.efi"},{"BootString":"sles12-secureboot","CorrelatableID":"PciRoot(0x0)/Pci(0x1,0x0)/Pci(0x0,0x0)","StructuredBootString":"HD.Emb.1.4","UEFIDevicePath":"PciRoot(0x0)/Pci(0x1,0x0)/Pci(0x0,0x0)/Scsi(0x0,0x0)/HD(3,GPT,91002AE5-E38D-4AE7-95F5-65C107287A02,0xEC1800,0x52000)/\\EFI\\sles12\\shim.efi"},{"BootString":"Red Hat Enterprise Linux","CorrelatableID":"PciRoot(0x0)/Pci(0x1,0x0)/Pci(0x0,0x0)","StructuredBootString":"HD.Emb.1.2","UEFIDevicePath":"PciRoot(0x0)/Pci(0x1,0x0)/Pci(0x0,0x0)/Scsi(0x0,0x0)/HD(1,GPT,2E732343-F550-48D6-923F-1982FAC86EC5,0x800,0x64000)/\\EFI\\redhat\\shim.efi"},{"BootString":"Red Hat Enterprise Linux","CorrelatableID":"PciRoot(0x0)/Pci(0x1,0x0)/Pci(0x0,0x0)","StructuredBootString":"HD.Emb.1.2","UEFIDevicePath":"PciRoot(0x0)/Pci(0x1,0x0)/Pci(0x0,0x0)/Scsi(0x0,0x0)/HD(1,GPT,2E732343-F550-48D6-923F-1982FAC86EC5,0x800,0x64000)/\\EFI\\redhat\\shim.efi"},{"BootString":"Red Hat Enterprise Linux","CorrelatableID":"PciRoot(0x0)/Pci(0x1,0x0)/Pci(0x0,0x0)","StructuredBootString":"HD.Emb.1.2","UEFIDevicePath":"PciRoot(0x0)/Pci(0x1,0x0)/Pci(0x0,0x0)/Scsi(0x0,0x0)/HD(1,GPT,2E732343-F550-48D6-923F-1982FAC86EC5,0x800,0x64000)/\\EFI\\redhat\\shim.efi"},{"BootString":"Red Hat Enterprise Linux","CorrelatableID":"PciRoot(0x0)/Pci(0x1,0x0)/Pci(0x0,0x0)","StructuredBootString":"HD.Emb.1.2","UEFIDevicePath":"PciRoot(0x0)/Pci(0x1,0x0)/Pci(0x0,0x0)/Scsi(0x0,0x0)/HD(1,GPT,2E732343-F550-48D6-923F-1982FAC86EC5,0x800,0x64000)/\\EFI\\redhat\\shim.efi"},{"BootString":"Red Hat Enterprise Linux","CorrelatableID":"PciRoot(0x0)/Pci(0x1,0x0)/Pci(0x0,0x0)","StructuredBootString":"HD.Emb.1.2","UEFIDevicePath":"PciRoot(0x0)/Pci(0x1,0x0)/Pci(0x0,0x0)/Scsi(0x0,0x0)/HD(1,GPT,2E732343-F550-48D6-923F-1982FAC86EC5,0x800,0x64000)/\\EFI\\redhat\\shim.efi"},{"BootString":"Embedded RAID : Smart Array P440ar Controller - 558.73 GiB, RAID 0 Logical Drive(Target:0, Lun:0)","CorrelatableID":"PciRoot(0x0)/Pci(0x1,0x0)/Pci(0x0,0x0)","StructuredBootString":"HD.Emb.1.3","UEFIDevicePath":"PciRoot(0x0)/Pci(0x1,0x0)/Pci(0x0,0x0)/Scsi(0x0,0x0)"}],"Description":"This is the Server Boot Order Current Settings","DesiredBootDevices":[{"CorrelatableID":"","Lun":"","Wwn":"","iScsiTargetName":""},{"CorrelatableID":"","Lun":"","Wwn":"","iScsiTargetName":""}],"Modified":"2019-03-26T19:58:11+00:00","Name":"Boot Order Current Settings","PersistentBootConfigOrder":["HD.Emb.1.6","HD.Emb.1.5","HD.Emb.1.4","HD.Emb.1.2","HD.Emb.1.2","HD.Emb.1.2","HD.Emb.1.2","HD.Emb.1.2","HD.Emb.1.3"],"SettingsResult":{"ETag":"","Messages":[{"MessageArgs":[],"MessageID":"Base.1.0:Success"}],"Time":""},"Type":"HpServerBootSettings.1.0.0","links":{"Settings":{"href":"/rest/v1/systems/1/bios/Boot/Settings"}}}