{"Message":"Security: Userid: dcmscan using the standard password had 99 login failures from WEB client at IP address 10.239.172.82.","MessageArgs":["dcmscan","the standard password","99","10.239.172.82"],"Id":"43033","Description":"This resource is used to represent a log entry for log services for a Redfish implementation.","EntryType":"Oem","Name":"LogEntry","EventGroupId":0,"OemLogEntryCode":"Lenovo0016","Oem":{"Lenovo":{"ReportingChain":"","IsLocalEvent":true,"RawDebugLogURL":"","AffectedIndicatorLEDs":[],"EventFlag":0,"AuxiliaryData":"","Source":"System","FailingFRU":[{"FRUSerialNumber":"","FRUNumber":""}],"TSLVersion":"0","CommonEventID":"FQXSPSE4002I","Hidden":false,"EventID":"0x4000001000000000","EventSequenceNumber":85752,"EventType":0,"@odata.type":"#LenovoLogEntry.v1_0_0.StandardLogEntry","LenovoMessageID":"Lenovo0016","TotalSequenceNumber":43033,"RelatedEventID":"","Serviceable":"Not Serviceable"}},"@odata.type":"#LogEntry.v1_4_3.LogEntry","OemRecordFormat":"Lenovo","Severity":"OK","@odata.etag":"\"d5a24f4d934ccf776fb90492b7e8c021\"","@odata.id":"/redfish/v1/Systems/1/LogServices/StandardLog/Entries/43033","Created":"2020-05-20T05:25:26.023+00:00"}