{"Message":"Security: Userid: USERID using the standard password had 95 login failures from WEB client at IP address 10.239.151.148.","MessageArgs":["USERID","the standard password","95","10.239.151.148"],"Id":"43408","Description":"This resource is used to represent a log entry for log services for a Redfish implementation.","EntryType":"Oem","Name":"LogEntry","EventGroupId":0,"OemLogEntryCode":"Lenovo0016","Oem":{"Lenovo":{"ReportingChain":"","IsLocalEvent":true,"RawDebugLogURL":"","AffectedIndicatorLEDs":[],"EventFlag":0,"AuxiliaryData":"","Source":"System","FailingFRU":[{"FRUSerialNumber":"","FRUNumber":""}],"TSLVersion":"0","CommonEventID":"FQXSPSE4002I","Hidden":false,"EventID":"0x4000001000000000","EventSequenceNumber":86511,"EventType":0,"@odata.type":"#LenovoLogEntry.v1_0_0.StandardLogEntry","LenovoMessageID":"Lenovo0016","TotalSequenceNumber":43408,"RelatedEventID":"","Serviceable":"Not Serviceable"}},"@odata.type":"#LogEntry.v1_4_3.LogEntry","OemRecordFormat":"Lenovo","Severity":"OK","@odata.etag":"\"516c99ddd3771292f77190f2593b6d7a\"","@odata.id":"/redfish/v1/Systems/1/LogServices/StandardLog/Entries/43408","Created":"2020-05-20T15:20:05.147+00:00"}