{
  "@Redfish.Settings": {
    "@odata.type": "#Settings.v1_3_0.Settings",
    "SettingsObject": {
      "@odata.id": "/redfish/v1/Systems/system/Bios/Settings"
    }
  },
  "@odata.id": "/redfish/v1/Systems/system/Bios",
  "@odata.type": "#Bios.v1_1_0.Bios",
  "Actions": {
    "#Bios.ChangePassword": {
      "target": "/redfish/v1/Systems/system/Bios/Actions/Bios.ChangePassword"
    },
    "#Bios.ResetBios": {
      "target": "/redfish/v1/Systems/system/Bios/Actions/Bios.ResetBios"
    }
  },
  "AttributeRegistry": "BiosAttributeRegistry",
  "Attributes": {
    "ACSViolationMask": "Disabled",
    "ADDDCEn": "Disabled",
    "AEPErrorInjEn": "Disabled",
    "ARIEnable": "Enabled",
    "ATS": "Enabled",
    "AcsControl": "Enabled",
    "ActiveCoreNum": "All",
    "AddinVideoAdapter": "Disabled",
    "AdvMemTestCondPause": 0,
    "AdvMemTestCondPmicVdd": 0,
    "AdvMemTestCondTrefi": 0,
    "AdvMemTestCondTwr": 0,
    "AdvMemTestCondition": "Auto",
    "AdvMemTestOptions": 0,
    "AdvMemTestPpr": "Enabled",
    "AdvMemTestRankListNumEntries": 0,
    "AdvMemTestResetList": "Disabled",
    "AdvMemTestRetryAfterRepair": "Enabled",
    "AtomicOpEgressBlockedMask": "Disabled",
    "AttemptFastBoot": "Enabled",
    "AttemptFastBootCold": "Enabled",
    "AvxIccpLevel": "128 Heavy",
    "AvxLicensePreGrant": "Disabled",
    "AvxP1Level": "Nominal",
    "BMCCheckFWVerDelay": 0,
    "BankSparing": "Disabled",
    "BootTimeout": 0,
    "C3Enable": "Disabled",
    "C6Enable": "Enabled",
    "CFRPucodeManualCommit": "Disabled",
    "CFRPucodeProvision": "Enabled",
    "CFRS3mManualCommit": "Disabled",
    "CFRS3mProvision": "Enabled",
    "Cb3NoSnoopEn_0": "Disabled",
    "Cb3NoSnoopEn_1": "Disabled",
    "Cb3NoSnoopEn_10": "Disabled",
    "Cb3NoSnoopEn_11": "Disabled",
    "Cb3NoSnoopEn_12": "Disabled",
    "Cb3NoSnoopEn_13": "Disabled",
    "Cb3NoSnoopEn_14": "Disabled",
    "Cb3NoSnoopEn_15": "Disabled",
    "Cb3NoSnoopEn_2": "Disabled",
    "Cb3NoSnoopEn_3": "Disabled",
    "Cb3NoSnoopEn_4": "Disabled",
    "Cb3NoSnoopEn_5": "Disabled",
    "Cb3NoSnoopEn_6": "Disabled",
    "Cb3NoSnoopEn_7": "Disabled",
    "Cb3NoSnoopEn_8": "Disabled",
    "Cb3NoSnoopEn_9": "Disabled",
    "CbRelaxedOrdering": "Disabled",
    "CoherencySupport": "Disabled",
    "CompletionTimeoutMask": "Disabled",
    "ConfigIOU0_1": "Auto",
    "ConfigIOU1_0": "Auto",
    "ConfigIOU1_0_inst_2": "Auto",
    "ConfigIOU1_0_inst_3": "Auto",
    "ConfigIOU1_1": "Auto",
    "ConfigIOU1_1_inst_2": "Auto",
    "ConfigIOU2_0": "Auto",
    "ConfigIOU2_0_inst_2": "Auto",
    "ConfigIOU2_1": "Auto",
    "ConfigIOU2_1_inst_2": "Auto",
    "ConfigIOU2_1_inst_3": "Auto",
    "ConfigIOU3_0": "Auto",
    "ConfigIOU3_0_inst_2": "Auto",
    "ConfigIOU3_1": "Auto",
    "ConfigIOU4_0": "Auto",
    "ConfigIOU4_0_inst_2": "Auto",
    "ConfigIOU4_1": "Auto",
    "ControlIommu": "Disabled",
    "CorrMemErrCmciEn": "Disabled",
    "CorrMemErrEn": "Enabled",
    "Cpu1DMIPcieMaxPayload": "128B",
    "CpuDbpEnable": "Disabled",
    "CpuPaLimit": "Disabled",
    "DCUIPPrefetcherEnable": "Enabled",
    "DCUStreamerPrefetcherEnable": "Enabled",
    "DFXEnable": "Disabled",
    "DataLinkProtocolErrMask": "Disabled",
    "DcpmmInvCfgRestrictedBoot": "Disabled",
    "DdrFreqLimit": "Auto",
    "DfxD2cEn": "Auto",
    "DfxD2kEn": "Auto",
    "DfxHitMeEn": "Auto",
    "DfxPmicVdd": 0,
    "DfxPmicVddQ": 0,
    "DirectoryModeEn": "Auto",
    "DisableDirForAppDirect": "Disabled",
    "DmaCtrlOptIn": "Disabled",
    "DynamicIss": "Disabled",
    "ECRCErrorMask": "Disabled",
    "EETurboDisable": "Enabled",
    "EPSDRASMode": "Maximum Performance",
    "EarlyBootTimeout": 0,
    "EcrcChkEn_1": "Disabled",
    "EcrcChkEn_10": "Disabled",
    "EcrcChkEn_11": "Disabled",
    "EcrcChkEn_12": "Disabled",
    "EcrcChkEn_13": "Disabled",
    "EcrcChkEn_14": "Disabled",
    "EcrcChkEn_15": "Disabled",
    "EcrcChkEn_16": "Disabled",
    "EcrcChkEn_17": "Disabled",
    "EcrcChkEn_18": "Disabled",
    "EcrcChkEn_19": "Disabled",
    "EcrcChkEn_2": "Disabled",
    "EcrcChkEn_20": "Disabled",
    "EcrcChkEn_21": "Disabled",
    "EcrcChkEn_22": "Disabled",
    "EcrcChkEn_23": "Disabled",
    "EcrcChkEn_24": "Disabled",
    "EcrcChkEn_25": "Disabled",
    "EcrcChkEn_26": "Disabled",
    "EcrcChkEn_27": "Disabled",
    "EcrcChkEn_28": "Disabled",
    "EcrcChkEn_29": "Disabled",
    "EcrcChkEn_3": "Disabled",
    "EcrcChkEn_30": "Disabled",
    "EcrcChkEn_31": "Disabled",
    "EcrcChkEn_32": "Disabled",
    "EcrcChkEn_33": "Disabled",
    "EcrcChkEn_34": "Disabled",
    "EcrcChkEn_35": "Disabled",
    "EcrcChkEn_36": "Disabled",
    "EcrcChkEn_37": "Disabled",
    "EcrcChkEn_38": "Disabled",
    "EcrcChkEn_39": "Disabled",
    "EcrcChkEn_4": "Disabled",
    "EcrcChkEn_40": "Disabled",
    "EcrcChkEn_5": "Disabled",
    "EcrcChkEn_58": "Disabled",
    "EcrcChkEn_59": "Disabled",
    "EcrcChkEn_6": "Disabled",
    "EcrcChkEn_60": "Disabled",
    "EcrcChkEn_61": "Disabled",
    "EcrcChkEn_62": "Disabled",
    "EcrcChkEn_63": "Disabled",
    "EcrcChkEn_64": "Disabled",
    "EcrcChkEn_65": "Disabled",
    "EcrcChkEn_66": "Disabled",
    "EcrcChkEn_67": "Disabled",
    "EcrcChkEn_68": "Disabled",
    "EcrcChkEn_69": "Disabled",
    "EcrcChkEn_7": "Disabled",
    "EcrcChkEn_70": "Disabled",
    "EcrcChkEn_71": "Disabled",
    "EcrcChkEn_72": "Disabled",
    "EcrcChkEn_73": "Disabled",
    "EcrcChkEn_74": "Disabled",
    "EcrcChkEn_75": "Disabled",
    "EcrcChkEn_76": "Disabled",
    "EcrcChkEn_77": "Disabled",
    "EcrcChkEn_78": "Disabled",
    "EcrcChkEn_79": "Disabled",
    "EcrcChkEn_8": "Disabled",
    "EcrcChkEn_80": "Disabled",
    "EcrcChkEn_81": "Disabled",
    "EcrcChkEn_82": "Disabled",
    "EcrcChkEn_83": "Disabled",
    "EcrcChkEn_84": "Disabled",
    "EcrcChkEn_85": "Disabled",
    "EcrcChkEn_86": "Disabled",
    "EcrcChkEn_87": "Disabled",
    "EcrcChkEn_88": "Disabled",
    "EcrcChkEn_89": "Disabled",
    "EcrcChkEn_9": "Disabled",
    "EcrcChkEn_90": "Disabled",
    "EcrcChkEn_91": "Disabled",
    "EcrcChkEn_92": "Disabled",
    "EcrcChkEn_93": "Disabled",
    "EcrcChkEn_94": "Disabled",
    "EcrcChkEn_95": "Disabled",
    "EcrcChkEn_96": "Disabled",
    "EcrcChkEn_97": "Disabled",
    "EcrcGenEn_1": "Disabled",
    "EcrcGenEn_10": "Disabled",
    "EcrcGenEn_11": "Disabled",
    "EcrcGenEn_12": "Disabled",
    "EcrcGenEn_13": "Disabled",
    "EcrcGenEn_14": "Disabled",
    "EcrcGenEn_15": "Disabled",
    "EcrcGenEn_16": "Disabled",
    "EcrcGenEn_17": "Disabled",
    "EcrcGenEn_18": "Disabled",
    "EcrcGenEn_19": "Disabled",
    "EcrcGenEn_2": "Disabled",
    "EcrcGenEn_20": "Disabled",
    "EcrcGenEn_21": "Disabled",
    "EcrcGenEn_22": "Disabled",
    "EcrcGenEn_23": "Disabled",
    "EcrcGenEn_24": "Disabled",
    "EcrcGenEn_25": "Disabled",
    "EcrcGenEn_26": "Disabled",
    "EcrcGenEn_27": "Disabled",
    "EcrcGenEn_28": "Disabled",
    "EcrcGenEn_29": "Disabled",
    "EcrcGenEn_3": "Disabled",
    "EcrcGenEn_30": "Disabled",
    "EcrcGenEn_31": "Disabled",
    "EcrcGenEn_32": "Disabled",
    "EcrcGenEn_33": "Disabled",
    "EcrcGenEn_34": "Disabled",
    "EcrcGenEn_35": "Disabled",
    "EcrcGenEn_36": "Disabled",
    "EcrcGenEn_37": "Disabled",
    "EcrcGenEn_38": "Disabled",
    "EcrcGenEn_39": "Disabled",
    "EcrcGenEn_4": "Disabled",
    "EcrcGenEn_40": "Disabled",
    "EcrcGenEn_5": "Disabled",
    "EcrcGenEn_58": "Disabled",
    "EcrcGenEn_59": "Disabled",
    "EcrcGenEn_6": "Disabled",
    "EcrcGenEn_60": "Disabled",
    "EcrcGenEn_61": "Disabled",
    "EcrcGenEn_62": "Disabled",
    "EcrcGenEn_63": "Disabled",
    "EcrcGenEn_64": "Disabled",
    "EcrcGenEn_65": "Disabled",
    "EcrcGenEn_66": "Disabled",
    "EcrcGenEn_67": "Disabled",
    "EcrcGenEn_68": "Disabled",
    "EcrcGenEn_69": "Disabled",
    "EcrcGenEn_7": "Disabled",
    "EcrcGenEn_70": "Disabled",
    "EcrcGenEn_71": "Disabled",
    "EcrcGenEn_72": "Disabled",
    "EcrcGenEn_73": "Disabled",
    "EcrcGenEn_74": "Disabled",
    "EcrcGenEn_75": "Disabled",
    "EcrcGenEn_76": "Disabled",
    "EcrcGenEn_77": "Disabled",
    "EcrcGenEn_78": "Disabled",
    "EcrcGenEn_79": "Disabled",
    "EcrcGenEn_8": "Disabled",
    "EcrcGenEn_80": "Disabled",
    "EcrcGenEn_81": "Disabled",
    "EcrcGenEn_82": "Disabled",
    "EcrcGenEn_83": "Disabled",
    "EcrcGenEn_84": "Disabled",
    "EcrcGenEn_85": "Disabled",
    "EcrcGenEn_86": "Disabled",
    "EcrcGenEn_87": "Disabled",
    "EcrcGenEn_88": "Disabled",
    "EcrcGenEn_89": "Disabled",
    "EcrcGenEn_9": "Disabled",
    "EcrcGenEn_90": "Disabled",
    "EcrcGenEn_91": "Disabled",
    "EcrcGenEn_92": "Disabled",
    "EcrcGenEn_93": "Disabled",
    "EcrcGenEn_94": "Disabled",
    "EcrcGenEn_95": "Disabled",
    "EcrcGenEn_96": "Disabled",
    "EcrcGenEn_97": "Disabled",
    "EdpcEn": "Disabled",
    "EdpcErrCorMsg": "Enabled",
    "EdpcInterrupt": "Enabled",
    "EliminateDirectoryInFarMemory": "Disabled",
    "EmcaEn": "Enabled",
    "EnableBiosSsaLoader": "Auto",
    "EnableBiosSsaRMT": "Auto",
    "EnableGlobalIntegrity": "Disabled",
    "EnableMktme": "Disabled",
    "EnableSgx": "Disabled",
    "EnableTme": "Disabled",
    "EnableTmeBypass": "Disabled",
    "EnforceDdrMemoryFreqPor": "Enforce POR",
    "EnforcePopulationPor": "Disable Enforcement",
    "EnforcedPasswd": "Disabled",
    "EpochUpdate": "Manual User Defined Owner EPOCHs",
    "FactoryResetClear": "Disabled",
    "FanSpdCtrlProfile": "Acoustic",
    "FastGoConfig": "Auto",
    "FastVideo": "Enabled",
    "FlowControlProtocolErrMask": "Disabled",
    "ForceErrorManager": "Disabled",
    "ForceFullSockets": "Disabled",
    "Frb2Timeout": "6 minutes",
    "FrontPanelLockOut": "Disabled",
    "HbmMemTest": "Disable HBM Memory Test",
    "HbmPprType": "PPR Disabled",
    "HwMemTest": "Enabled",
    "I3cSpeed": "Auto",
    "IPv4PXESupport": "Enabled",
    "IPv6PXESupport": "Enabled",
    "IioErrRegistersClearEn": "Enabled",
    "IioErrorEn": "Enabled",
    "ImcChaMcaCsmiEn": "Disabled",
    "InputUncoreFreq": 0,
    "IoDcMode": "Auto",
    "IssTdpLevel": "Level 0",
    "KtiPrefetchEn": "Auto",
    "LLCDeadLineAlloc": "Enabled",
    "LatchSystemShutdownState": "Enabled",
    "LegacyVgaSocket": "CPU Socket 0",
    "LlcPrefetchEnable": "Enabled",
    "LockChipset": "Enabled",
    "MCBlockedTLPMask": "Disabled",
    "MalformedTLPMask": "Disabled",
    "McBankWarmBootClearError": "Enabled",
    "MctpBroadcastCycle": "Enabled",
    "MemHotIn": "Disabled",
    "MemHotOuputAssertThreshold": "Enable only temphi",
    "MemHotOut": "Enabled",
    "MemTestLoops": 0,
    "MemTripReporting": "Enabled",
    "MirrorMode": "Disabled",
    "MlcSpatialPrefetcherEnable": "Enabled",
    "MlcStreamerPrefetcherEnable": "Enabled",
    "MmiohBase": "56T",
    "MmiohSize": "256G",
    "NgnArsPublish": "Enabled",
    "NgnDebugLock": "Disabled",
    "NtbBarSizeEmBarSZ1_1": 0,
    "NtbBarSizeEmBarSZ1_11": 0,
    "NtbBarSizeEmBarSZ1_2": 0,
    "NtbBarSizeEmBarSZ1_3": 0,
    "NtbBarSizeEmBarSZ1_4": 0,
    "NtbBarSizeEmBarSZ1_8": 0,
    "NtbBarSizeEmBarSZ1_9": 0,
    "NtbBarSizeEmBarSZ2_0_1": 0,
    "NtbBarSizeEmBarSZ2_0_11": 0,
    "NtbBarSizeEmBarSZ2_0_2": 0,
    "NtbBarSizeEmBarSZ2_0_3": 0,
    "NtbBarSizeEmBarSZ2_0_4": 0,
    "NtbBarSizeEmBarSZ2_0_8": 0,
    "NtbBarSizeEmBarSZ2_0_9": 0,
    "NtbBarSizeEmBarSZ2_1": 0,
    "NtbBarSizeEmBarSZ2_11": 0,
    "NtbBarSizeEmBarSZ2_1_1": 0,
    "NtbBarSizeEmBarSZ2_1_11": 0,
    "NtbBarSizeEmBarSZ2_1_2": 0,
    "NtbBarSizeEmBarSZ2_1_3": 0,
    "NtbBarSizeEmBarSZ2_1_4": 0,
    "NtbBarSizeEmBarSZ2_1_8": 0,
    "NtbBarSizeEmBarSZ2_1_9": 0,
    "NtbBarSizeEmBarSZ2_2": 0,
    "NtbBarSizeEmBarSZ2_3": 0,
    "NtbBarSizeEmBarSZ2_4": 0,
    "NtbBarSizeEmBarSZ2_8": 0,
    "NtbBarSizeEmBarSZ2_9": 0,
    "NtbBarSizeImBar1_1": 0,
    "NtbBarSizeImBar1_11": 0,
    "NtbBarSizeImBar1_2": 0,
    "NtbBarSizeImBar1_3": 0,
    "NtbBarSizeImBar1_4": 0,
    "NtbBarSizeImBar1_8": 0,
    "NtbBarSizeImBar1_9": 0,
    "NtbBarSizeImBar2_0_1": 0,
    "NtbBarSizeImBar2_0_11": 0,
    "NtbBarSizeImBar2_0_2": 0,
    "NtbBarSizeImBar2_0_3": 0,
    "NtbBarSizeImBar2_0_4": 0,
    "NtbBarSizeImBar2_0_8": 0,
    "NtbBarSizeImBar2_0_9": 0,
    "NtbBarSizeImBar2_1": 0,
    "NtbBarSizeImBar2_11": 0,
    "NtbBarSizeImBar2_1_1": 0,
    "NtbBarSizeImBar2_1_11": 0,
    "NtbBarSizeImBar2_1_2": 0,
    "NtbBarSizeImBar2_1_3": 0,
    "NtbBarSizeImBar2_1_4": 0,
    "NtbBarSizeImBar2_1_8": 0,
    "NtbBarSizeImBar2_1_9": 0,
    "NtbBarSizeImBar2_2": 0,
    "NtbBarSizeImBar2_3": 0,
    "NtbBarSizeImBar2_4": 0,
    "NtbBarSizeImBar2_8": 0,
    "NtbBarSizeImBar2_9": 0,
    "NtbBarSizeOverride_1": "Disabled",
    "NtbBarSizeOverride_11": "Disabled",
    "NtbBarSizeOverride_2": "Disabled",
    "NtbBarSizeOverride_3": "Disabled",
    "NtbBarSizeOverride_4": "Disabled",
    "NtbBarSizeOverride_8": "Disabled",
    "NtbBarSizeOverride_9": "Disabled",
    "NtbLinkBiosTrainEn": "Yes",
    "NtbPpd_1": "Transparent Bridge",
    "NtbPpd_11": "Transparent Bridge",
    "NtbPpd_2": "Transparent Bridge",
    "NtbPpd_3": "Transparent Bridge",
    "NtbPpd_4": "Transparent Bridge",
    "NtbPpd_8": "Transparent Bridge",
    "NtbPpd_9": "Transparent Bridge",
    "NtbSplitBar_1": "Disabled",
    "NtbSplitBar_11": "Disabled",
    "NtbSplitBar_2": "Disabled",
    "NtbSplitBar_3": "Disabled",
    "NtbSplitBar_4": "Disabled",
    "NtbSplitBar_8": "Disabled",
    "NtbSplitBar_9": "Disabled",
    "NtbXlinkCtlOverride_1": "DSD/USP",
    "NtbXlinkCtlOverride_11": "DSD/USP",
    "NtbXlinkCtlOverride_2": "DSD/USP",
    "NtbXlinkCtlOverride_3": "DSD/USP",
    "NtbXlinkCtlOverride_4": "DSD/USP",
    "NtbXlinkCtlOverride_8": "DSD/USP",
    "NtbXlinkCtlOverride_9": "DSD/USP",
    "NumaEn": "Enabled",
    "NvmQos": "Disabled",
    "NvmdimmPerfConfig": "Balanced Profile",
    "NvmdimmPowerCyclePolicy": "Enabled",
    "OSBootWDTimer": "Disabled",
    "OSBootWDTimerPolicy": "Power Off",
    "OSBootWDTimerTimeout": "10 minutes",
    "OnboardNICEnable_0": "Enabled",
    "OnboardVideo": "Enabled",
    "OsNativeAerSupport": "Disabled",
    "PCIECorrErrorEn": "Enabled",
    "PackageCState": "Auto",
    "PagePolicy": "Closed",
    "PatrolScrub": "Enable at End of POST",
    "PcieAspm_1": "Auto",
    "PcieAspm_10": "Auto",
    "PcieAspm_11": "Auto",
    "PcieAspm_12": "Auto",
    "PcieAspm_13": "Auto",
    "PcieAspm_14": "Auto",
    "PcieAspm_15": "Auto",
    "PcieAspm_16": "Auto",
    "PcieAspm_17": "Auto",
    "PcieAspm_18": "Auto",
    "PcieAspm_19": "Auto",
    "PcieAspm_2": "Auto",
    "PcieAspm_20": "Auto",
    "PcieAspm_21": "Auto",
    "PcieAspm_22": "Auto",
    "PcieAspm_23": "Auto",
    "PcieAspm_24": "Auto",
    "PcieAspm_25": "Auto",
    "PcieAspm_26": "Auto",
    "PcieAspm_27": "Auto",
    "PcieAspm_28": "Auto",
    "PcieAspm_29": "Auto",
    "PcieAspm_3": "Auto",
    "PcieAspm_30": "Auto",
    "PcieAspm_31": "Auto",
    "PcieAspm_32": "Auto",
    "PcieAspm_33": "Auto",
    "PcieAspm_34": "Auto",
    "PcieAspm_35": "Auto",
    "PcieAspm_36": "Auto",
    "PcieAspm_37": "Auto",
    "PcieAspm_38": "Auto",
    "PcieAspm_39": "Auto",
    "PcieAspm_4": "Auto",
    "PcieAspm_40": "Auto",
    "PcieAspm_5": "Auto",
    "PcieAspm_58": "Auto",
    "PcieAspm_59": "Auto",
    "PcieAspm_6": "Auto",
    "PcieAspm_60": "Auto",
    "PcieAspm_61": "Auto",
    "PcieAspm_62": "Auto",
    "PcieAspm_63": "Auto",
    "PcieAspm_64": "Auto",
    "PcieAspm_65": "Auto",
    "PcieAspm_66": "Auto",
    "PcieAspm_67": "Auto",
    "PcieAspm_68": "Auto",
    "PcieAspm_69": "Auto",
    "PcieAspm_7": "Auto",
    "PcieAspm_70": "Auto",
    "PcieAspm_71": "Auto",
    "PcieAspm_72": "Auto",
    "PcieAspm_73": "Auto",
    "PcieAspm_74": "Auto",
    "PcieAspm_75": "Auto",
    "PcieAspm_76": "Auto",
    "PcieAspm_77": "Auto",
    "PcieAspm_78": "Auto",
    "PcieAspm_79": "Auto",
    "PcieAspm_8": "Auto",
    "PcieAspm_80": "Auto",
    "PcieAspm_81": "Auto",
    "PcieAspm_82": "Auto",
    "PcieAspm_83": "Auto",
    "PcieAspm_84": "Auto",
    "PcieAspm_85": "Auto",
    "PcieAspm_86": "Auto",
    "PcieAspm_87": "Auto",
    "PcieAspm_88": "Auto",
    "PcieAspm_89": "Auto",
    "PcieAspm_9": "Auto",
    "PcieAspm_90": "Auto",
    "PcieAspm_91": "Auto",
    "PcieAspm_92": "Auto",
    "PcieAspm_93": "Auto",
    "PcieAspm_94": "Auto",
    "PcieAspm_95": "Auto",
    "PcieAspm_96": "Auto",
    "PcieAspm_97": "Auto",
    "PcieCeErrThreshold": "20",
    "PcieGlobalAspm": "Per-Port",
    "PciePllSsc": "Auto",
    "PciePortEnable_1": "Auto",
    "PciePortEnable_10": "Auto",
    "PciePortEnable_11": "Auto",
    "PciePortEnable_12": "Auto",
    "PciePortEnable_13": "Auto",
    "PciePortEnable_14": "Auto",
    "PciePortEnable_15": "Auto",
    "PciePortEnable_16": "Auto",
    "PciePortEnable_17": "Auto",
    "PciePortEnable_18": "Auto",
    "PciePortEnable_19": "Auto",
    "PciePortEnable_2": "Auto",
    "PciePortEnable_20": "Auto",
    "PciePortEnable_21": "Auto",
    "PciePortEnable_22": "Auto",
    "PciePortEnable_23": "Auto",
    "PciePortEnable_24": "Auto",
    "PciePortEnable_25": "Auto",
    "PciePortEnable_26": "Auto",
    "PciePortEnable_27": "Auto",
    "PciePortEnable_28": "Auto",
    "PciePortEnable_29": "Auto",
    "PciePortEnable_3": "Auto",
    "PciePortEnable_30": "Auto",
    "PciePortEnable_31": "Auto",
    "PciePortEnable_32": "Auto",
    "PciePortEnable_33": "Auto",
    "PciePortEnable_34": "Auto",
    "PciePortEnable_35": "Auto",
    "PciePortEnable_36": "Auto",
    "PciePortEnable_37": "Auto",
    "PciePortEnable_38": "Auto",
    "PciePortEnable_39": "Auto",
    "PciePortEnable_4": "Auto",
    "PciePortEnable_5": "Auto",
    "PciePortEnable_58": "Auto",
    "PciePortEnable_59": "Auto",
    "PciePortEnable_6": "Auto",
    "PciePortEnable_60": "Auto",
    "PciePortEnable_61": "Auto",
    "PciePortEnable_62": "Auto",
    "PciePortEnable_63": "Auto",
    "PciePortEnable_64": "Auto",
    "PciePortEnable_65": "Auto",
    "PciePortEnable_66": "Auto",
    "PciePortEnable_67": "Auto",
    "PciePortEnable_68": "Auto",
    "PciePortEnable_69": "Auto",
    "PciePortEnable_7": "Auto",
    "PciePortEnable_70": "Auto",
    "PciePortEnable_71": "Auto",
    "PciePortEnable_72": "Auto",
    "PciePortEnable_73": "Auto",
    "PciePortEnable_74": "Auto",
    "PciePortEnable_75": "Auto",
    "PciePortEnable_76": "Auto",
    "PciePortEnable_77": "Auto",
    "PciePortEnable_78": "Auto",
    "PciePortEnable_79": "Auto",
    "PciePortEnable_8": "Auto",
    "PciePortEnable_80": "Auto",
    "PciePortEnable_81": "Auto",
    "PciePortEnable_82": "Auto",
    "PciePortEnable_83": "Auto",
    "PciePortEnable_84": "Auto",
    "PciePortEnable_85": "Auto",
    "PciePortEnable_86": "Auto",
    "PciePortEnable_87": "Auto",
    "PciePortEnable_88": "Auto",
    "PciePortEnable_89": "Auto",
    "PciePortEnable_9": "Auto",
    "PciePortEnable_90": "Auto",
    "PciePortEnable_91": "Auto",
    "PciePortEnable_92": "Auto",
    "PciePortEnable_93": "Auto",
    "PciePortEnable_94": "Auto",
    "PciePortEnable_95": "Auto",
    "PciePortEnable_96": "Auto",
    "PciePortEnable_97": "Auto",
    "PciePortLinkSpeed_S_1": "Gen 5",
    "PciePortLinkSpeed_S_11": "Gen 5",
    "PciePortLinkSpeed_S_13": "Gen 5",
    "PciePortLinkSpeed_S_15": "Gen 5",
    "PciePortLinkSpeed_S_17": "Gen 5",
    "PciePortLinkSpeed_S_19": "Gen 5",
    "PciePortLinkSpeed_S_21": "Gen 5",
    "PciePortLinkSpeed_S_23": "Gen 5",
    "PciePortLinkSpeed_S_25": "Gen 5",
    "PciePortLinkSpeed_S_27": "Gen 5",
    "PciePortLinkSpeed_S_29": "Gen 5",
    "PciePortLinkSpeed_S_3": "Gen 5",
    "PciePortLinkSpeed_S_31": "Gen 5",
    "PciePortLinkSpeed_S_33": "Gen 5",
    "PciePortLinkSpeed_S_35": "Gen 5",
    "PciePortLinkSpeed_S_37": "Gen 5",
    "PciePortLinkSpeed_S_39": "Gen 5",
    "PciePortLinkSpeed_S_5": "Gen 5",
    "PciePortLinkSpeed_S_58": "Gen 5",
    "PciePortLinkSpeed_S_60": "Gen 5",
    "PciePortLinkSpeed_S_62": "Gen 5",
    "PciePortLinkSpeed_S_64": "Gen 5",
    "PciePortLinkSpeed_S_66": "Gen 5",
    "PciePortLinkSpeed_S_68": "Gen 5",
    "PciePortLinkSpeed_S_7": "Gen 5",
    "PciePortLinkSpeed_S_70": "Gen 5",
    "PciePortLinkSpeed_S_72": "Gen 5",
    "PciePortLinkSpeed_S_74": "Gen 5",
    "PciePortLinkSpeed_S_76": "Gen 5",
    "PciePortLinkSpeed_S_78": "Gen 5",
    "PciePortLinkSpeed_S_80": "Gen 5",
    "PciePortLinkSpeed_S_82": "Gen 5",
    "PciePortLinkSpeed_S_84": "Gen 5",
    "PciePortLinkSpeed_S_86": "Gen 5",
    "PciePortLinkSpeed_S_88": "Gen 5",
    "PciePortLinkSpeed_S_9": "Gen 5",
    "PciePortLinkSpeed_S_90": "Gen 5",
    "PciePortLinkSpeed_S_92": "Gen 5",
    "PciePortLinkSpeed_S_94": "Gen 5",
    "PciePortLinkSpeed_S_96": "Gen 5",
    "PciePtlpEgrBlk": "Enabled",
    "PclsEn": "Enabled",
    "PerfPLimitEn": "Enabled",
    "PfrLock": "Disabled",
    "PfrProvision": "Disabled",
    "PfrUnProvision": "Disabled",
    "PmaxOffset": 0,
    "PmaxSign": "Positive",
    "PoisonEn": "Enabled",
    "PoisonedTLPMask": "Disabled",
    "PowerOnPassword": "Disabled",
    "PrmSgxSize": "No valid PRM size",
    "ProcessorAPSrocketing": "Disabled",
    "ProcessorActivePbf": "Disabled",
    "ProcessorC1eEnable": "Enabled",
    "ProcessorConfigurePbf": "Enabled",
    "ProcessorEPPEnable": "Enabled",
    "ProcessorEistEnable": "Enabled",
    "ProcessorEistPsdFunc": "HW_ALL",
    "ProcessorHWPMEnable": "Native Mode",
    "ProcessorHWPMInterrupt": "Disabled",
    "ProcessorHyperThreadingDisable": "Enabled",
    "ProcessorPowerPolicy": "Balanced Performance",
    "ProcessorScalability": "Disabled",
    "ProcessorSmxEnable": "Disabled",
    "ProcessorSstCpSetting": "Disabled",
    "ProcessorVmxEnable": "Enabled",
    "ProcessorX2apic": "Disabled",
    "PropagatePerr": "Enabled",
    "PropagateSerr": "Enabled",
    "QpiLinkSpeed": "Auto",
    "QuietBoot": "Enabled",
    "RandomPowerOnDelayValue": 0,
    "RandomPowerPolicy": "Disabled",
    "RasLogLevel": "MIN (BASIC_FLOW)",
    "ReceiverOverflowMask": "Disabled",
    "ResetCaterr": "Enabled",
    "ResetErr2": "Enabled",
    "SRIOVEnable": "Enabled",
    "SataInterfaceMode_0": "AHCI",
    "SataInterfaceMode_1": "AHCI",
    "SataInterfaceMode_2": "AHCI",
    "SataPort_0": "Enabled",
    "SataPort_1": "Enabled",
    "SataPort_10": "Enabled",
    "SataPort_11": "Enabled",
    "SataPort_12": "Enabled",
    "SataPort_13": "Enabled",
    "SataPort_14": "Enabled",
    "SataPort_15": "Enabled",
    "SataPort_2": "Enabled",
    "SataPort_3": "Enabled",
    "SataPort_4": "Enabled",
    "SataPort_5": "Enabled",
    "SataPort_6": "Enabled",
    "SataPort_7": "Enabled",
    "SataPort_8": "Enabled",
    "SataPort_9": "Enabled",
    "SataSpinUpOption_0": "Disabled",
    "SataSpinUpOption_1": "Disabled",
    "SataSpinUpOption_2": "Disabled",
    "SataTestMode_0": "Disabled",
    "SataTestMode_1": "Disabled",
    "ScrambleEn": "Enabled",
    "ScrambleEnDDRT": "Enabled",
    "SerialA": "Enabled",
    "SerialAIo": "3F8h",
    "SerialB": "Disabled",
    "SerialBIo": "2F8h",
    "SerialOverLanEnable_0": "Disabled",
    "SerialOverLanEnable_2": "Disabled",
    "SgxAutoRegistrationAgent": "Disabled",
    "SgxFactoryReset": "Disabled",
    "SgxLeWr": "Enabled",
    "SgxPackageInfoInBandAccess": "Disabled",
    "SgxQoS": "Enabled",
    "SncEn": "AUTO",
    "SnoopResponseHoldOff": 0,
    "SparePerBankTh": 0,
    "SpsMctpBusOwner": 0,
    "StaleAtoSOptEn": "Disabled",
    "SurpriseDownErrMask": "Disabled",
    "SvidEnable": "Enabled",
    "SvidVoltageOverride": 0,
    "SvrMngmntAcpiIpmi": "Disabled",
    "SvrMngmntConsRedirSerial1BitRate": "115.2K",
    "SvrMngmntConsRedirSerial1ConnectionType": "VT100",
    "SvrMngmntConsRedirSerial1FlowCtrl": "None",
    "SvrMngmntConsRedirSerialEnable": "Disabled",
    "SvrMngmntDiagnosticMsgEnable": "Enabled",
    "SvrMngmntFrb2Enable": "Enabled",
    "SystemErrorEn": "Enabled",
    "TLPPrefixBlockedErrMask": "Disabled",
    "TerminalResolution": "80x25",
    "ThreeStrikeTimer": "Enabled",
    "TimeWindow": 0,
    "Tpm2FwUpdateEnable": "Disabled",
    "Tpm2Operation": "No Action",
    "TpmOperation": "No Operation",
    "TriggerSWErrThEn": "Disabled",
    "TurboMode": "Enabled",
    "UEFINetworkStack": "Enabled",
    "UmaBasedClustering": "Quadrant   (4-clusters)",
    "UncoreFreqRaplLimit": "Enabled",
    "UncoreFreqScaling": "Enabled",
    "UncorrectableInternalErrorMask": "Disabled",
    "UnexpectedCompletionMask": "Disabled",
    "UsbBootPriorityEnabled": "Enabled",
    "UsbFrontPortsEn": "Enabled",
    "UsbInternalPortsEn": "Enabled",
    "UsbRearPortsEn": "Enabled",
    "VDimmVdd": 0,
    "VDimmVddEnable": "Disabled",
    "VMDDirectAssign_0": "Disabled",
    "VMDDirectAssign_1": "Disabled",
    "VMDDirectAssign_10": "Disabled",
    "VMDDirectAssign_12": "Disabled",
    "VMDDirectAssign_13": "Disabled",
    "VMDDirectAssign_3": "Disabled",
    "VMDDirectAssign_4": "Disabled",
    "VMDDirectAssign_5": "Disabled",
    "VMDDirectAssign_9": "Disabled",
    "VTdSupport": "Enabled",
    "ViralEn": "Disabled",
    "VmdEnable_0": "Disabled",
    "VmdEnable_1": "Disabled",
    "VmdEnable_10": "Disabled",
    "VmdEnable_12": "Disabled",
    "VmdEnable_13": "Disabled",
    "VmdEnable_3": "Disabled",
    "VmdEnable_4": "Disabled",
    "VmdEnable_5": "Disabled",
    "VmdEnable_9": "Disabled",
    "VmdPchPortEnable_0": "Disabled",
    "VmdPchPortEnable_1": "Disabled",
    "VmdPortEnable_100": "Disabled",
    "VmdPortEnable_102": "Disabled",
    "VmdPortEnable_104": "Disabled",
    "VmdPortEnable_106": "Disabled",
    "VmdPortEnable_108": "Disabled",
    "VmdPortEnable_110": "Disabled",
    "VmdPortEnable_24": "Disabled",
    "VmdPortEnable_26": "Disabled",
    "VmdPortEnable_28": "Disabled",
    "VmdPortEnable_30": "Disabled",
    "VmdPortEnable_32": "Disabled",
    "VmdPortEnable_34": "Disabled",
    "VmdPortEnable_36": "Disabled",
    "VmdPortEnable_38": "Disabled",
    "VmdPortEnable_40": "Disabled",
    "VmdPortEnable_42": "Disabled",
    "VmdPortEnable_44": "Disabled",
    "VmdPortEnable_46": "Disabled",
    "VmdPortEnable_72": "Disabled",
    "VmdPortEnable_74": "Disabled",
    "VmdPortEnable_76": "Disabled",
    "VmdPortEnable_78": "Disabled",
    "VmdPortEnable_8": "Disabled",
    "VmdPortEnable_86": "Disabled",
    "VmdPortEnable_96": "Disabled",
    "VmdPortEnable_98": "Disabled",
    "WheaSupport": "Enabled",
    "WorkLdConfig": "Balanced",
    "bdatEn": "Disabled",
    "eraseArmNVDIMMS": "Enabled",
    "interNVDIMMS": "Disabled",
    "memhotSupport": "Enabled",
    "multiSparingRanks": "2 Rank",
    "partialmirrorsad0": "Disabled",
    "partialmirrorsize_0": 0,
    "partialmirrorsize_1": 0,
    "partialmirrorsize_2": 0,
    "partialmirrorsize_3": 0,
    "pprType": "Soft PPR",
    "promoteWarnings": "Disabled",
    "restoreNVDIMMS": "Enabled",
    "serialDebugMsgLvl": "Auto",
    "spareErrTh": "10",
    "thermalthrottlingsupport": "CLTT",
    "volMemMode": "2LM"
  },
  "Description": "BIOS Configuration Service",
  "Id": "BIOS",
  "Links": {
    "ActiveSoftwareImage": {
      "@odata.id": "/redfish/v1/UpdateService/FirmwareInventory/bios_active"
    },
    "SoftwareImages": [
      {
        "@odata.id": "/redfish/v1/UpdateService/FirmwareInventory/bios_active"
      },
      {
        "@odata.id": "/redfish/v1/UpdateService/FirmwareInventory/bios_recovery"
      }
    ],
    "SoftwareImages@odata.count": 2
  },
  "Name": "BIOS Configuration",
  "Oem": {
    "OpenBmc": {
      "@odata.type": "#OemBios.v1_0_0.OpenBmc",
      "BypassBiosPassword": {
        "@odata.type": "#OemBios.v1_0_0.BypassBiosPassword",
        "CurrentValue": false
      },
      "PostCode": {
        "@odata.type": "#OemBios.v1_0_0.PostCode",
        "CurrentBootCycleCount": 20,
        "CurrentCycleCount": 1,
        "MaxBootCycleNum": 100,
        "PreviousCycleCount": 2
      }
    }
  }
}